srctag/__init__.py
srctag/cli.py
srctag/collector.py
srctag/model.py
srctag/storage.py
srctag/tagger.py
srctag-0.5.1.dist-info/LICENSE
srctag-0.5.1.dist-info/METADATA
srctag-0.5.1.dist-info/WHEEL
srctag-0.5.1.dist-info/entry_points.txt
srctag-0.5.1.dist-info/RECORD
