Metadata-Version: 2.1
Name: srctag
Version: 0.5.1
Summary: Tag source files with real-world stories.
License: Apache-2.0
Author: williamfzc
Author-email: williamfzc@foxmail.com
Requires-Python: >=3.8,<4.0
Classifier: License :: OSI Approved :: Apache Software License
Classifier: Programming Language :: Python :: 3
Classifier: Programming Language :: Python :: 3.8
Classifier: Programming Language :: Python :: 3.9
Classifier: Programming Language :: Python :: 3.10
Classifier: Programming Language :: Python :: 3.11
Classifier: Programming Language :: Python :: 3.12
Provides-Extra: embedding
Requires-Dist: chromadb (==0.4.14)
Requires-Dist: click (>=8.1.3,<9.0.0)
Requires-Dist: gitpython
Requires-Dist: loguru (>=0.7.2,<0.8.0)
Requires-Dist: matplotlib
Requires-Dist: networkx (>=3.1,<4.0)
Requires-Dist: pandas (>=2.0.3,<3.0.0)
Requires-Dist: pydantic
Requires-Dist: pydantic-settings
Requires-Dist: pydot (>=1.4.2,<2.0.0)
Requires-Dist: sentence-transformers (>=2.2.2,<3.0.0) ; extra == "embedding"
Requires-Dist: tqdm
